{
  "addressesObjects": [
    {
      "building_name": "",
      "building_number": "1",
      "country": "England",
      "county": "East Sussex",
      "district": "Lewes",
      "formatted_address": [
        "1 North Barnes Lane",
        "",
        "",
        "Plumpton Green, Lewes",
        "East Sussex"
      ],
      "line_1": "1 North Barnes Lane",
      "line_2": "",
      "line_3": "",
      "line_4": "",
      "locality": "Plumpton Green",
      "sub_building_name": "",
      "sub_building_number": "",
      "thoroughfare": "North Barnes Lane",
      "town_or_city": "Lewes"
    },
    {
      "building_name": "",
      "building_number": "2",
      "country": "England",
      "county": "East Sussex",
      "district": "Lewes",
      "formatted_address": [
        "2 North Barnes Lane",
        "",
        "",
        "Plumpton Green, Lewes",
        "East Sussex"
      ],
      "line_1": "2 North Barnes Lane",
      "line_2": "",
      "line_3": "",
      "line_4": "",
      "locality": "Plumpton Green",
      "sub_building_name": "",
      "sub_building_number": "",
      "thoroughfare": "North Barnes Lane",
      "town_or_city": "Lewes"
    },
    {
      "building_name": "South View",
      "building_number": "2",
      "country": "England",
      "county": "East Sussex",
      "district": "Lewes",
      "formatted_address": [
        "2 South View",
        "North Barnes Lane",
        "",
        "Plumpton Green, Lewes",
        "East Sussex"
      ],
      "line_1": "2 South View",
      "line_2": "North Barnes Lane",
      "line_3": "",
      "line_4": "",
      "locality": "Plumpton Green",
      "sub_building_name": "",
      "sub_building_number": "",
      "thoroughfare": "North Barnes Lane",
      "town_or_city": "Lewes"
    }
  ],
  "am": [
    "AM",
    "PM",
    "NULL"
  ],
  "bookingDate": "10-03-2023",
  "bookingDateTime": "",
  "bookingFinished": false,
  "bookingID": "",
  "bookingPatientId": "",
  "bookingResponse": "Sorry, something went wrong, please select a different slot",
  "bookingTime": "08:30",
  "cancellationError": "Booking has changed, please cancel booking in Compucare.",
  "cancellationSuccess": false,
  "clinicid": "47",
  "condition": "Cataract",
  "conditionFinal": "Cataract",
  "consultant": "Ananth C. Viswanathan",
  "conversionId": "a0A3H000006O0sXUAS",
  "createAddress": "",
  "createAddress2": "",
  "createCity": "",
  "createCountry": "",
  "createCounty": "",
  "createDob": "",
  "createEmail": "",
  "createHome": "",
  "createInternationalPhone": "",
  "createMobile": "07358844456",
  "createPostCode": "",
  "createSalutation": "",
  "createSex": "",
  "creationError": "",
  "date": "28-03-2023",
  "dateWeek": "2023-03-23",
  "datesToShow": [
    "2023-03-24",
    "2023-03-28",
    "2023-03-29"
  ],
  "dob": "",
  "duration": 30,
  "editError": "",
  "failedBooking": false,
  "firstName": "Tammy",
  "insurer": "SELF",
  "isBookingCancellable": false,
  "lastName": "Taylor",
  "loadingBooking": false,
  "loadingBookingData": false,
  "location": "Moorfields Private Outpatient Centre",
  "locations": [
    "Bedford",
    "Moorfields Private Outpatient Centre",
    "New Cavendish Street",
    "Northwick Park",
    "Purley",
    "Richard Desmond Children's Eye Centre"
  ],
  "noPatientsFound": false,
  "onlyVisualFields": false,
  "params": {
    "ageRange": "21",
    "bookingID": "",
    "condition": "Cataract",
    "conditionFinal": "Cataract",
    "consultant": "",
    "conversionId": "a0A3H000006O0sXUAS",
    "dob": "",
    "email": "",
    "firstName": "Tammy",
    "gender": "",
    "insurer": "SELF",
    "lastName": "Taylor",
    "mobile": "07358844456",
    "sharedCare": "false",
    "speciality": "Cataracts",
    "tab": "-MWZUnL0Mw7L_6bo6jKO",
    "userId": "0054L0000018XYoQAM"
  },
  "paramsConsultant": "",
  "paramsUserId": "0054L0000018XYoQAM",
  "patientCreated": false,
  "patientEdit": false,
  "patientEdited": false,
  "patientSystemNumber": "0309532",
  "refreshAppointments": false,
  "searchSex": "Female",
  "showCreatePatient": false,
  "solutionId": "a0H4L000001RMUIUA4",
  "solutionName": "VISWANATHAN - Cataracts - Cataract",
  "speciality": "Cataracts",
  "successfulBooking": false,
  "time": "09:30",
  "timeOffset": "08:30",
  "validationAlert": "",
  "validationDOB": "",
  "validationSex": "",
  "visual": "select",
  "visualBookingDateTime": "",
  "visualBookingID": "",
  "visualClinicid": "",
  "visualConsultant": "",
  "visualDate": "",
  "visualDuration": "",
  "visualLocation": "",
  "visualSolutionName": "Visual Fields Test - A",
  "visualTime": "",
  "visualTimeOffset": ""
}